libchebipy/__init__.py
libchebipy/_base_object.py
libchebipy/_chebi_entity.py
libchebipy/_comment.py
libchebipy/_compound_origin.py
libchebipy/_database_accession.py
libchebipy/_formula.py
libchebipy/_name.py
libchebipy/_parsers.py
libchebipy/_reference.py
libchebipy/_relation.py
libchebipy/_structure.py
libchebipy/test/__init__.py
libchebipy/test/test_libchebipy.py
libChEBIpy-1.0.10.dist-info/LICENCE
libChEBIpy-1.0.10.dist-info/METADATA
libChEBIpy-1.0.10.dist-info/WHEEL
libChEBIpy-1.0.10.dist-info/top_level.txt
libChEBIpy-1.0.10.dist-info/RECORD
