Metadata-Version: 1.1
Name: libChEBIpy
Version: 1.0.10
Summary: libChEBIpy: a Python API for accessing the ChEBI database
Home-page: http://github.com/synbiochem/libChEBIpy
Author: Neil Swainston
Author-email: neil.swainston@manchester.ac.uk
License: MIT
Keywords: chemistry cheminformatics ChEBI
Platform: UNKNOWN
Classifier: Development Status :: 5 - Production/Stable
Classifier: Intended Audience :: Developers
Classifier: Topic :: Software Development :: Build Tools
Classifier: License :: OSI Approved :: MIT License
Classifier: Programming Language :: Python :: 2.7
